nqrduck_pulseprogrammer/__init__.py
nqrduck_pulseprogrammer/controller.py
nqrduck_pulseprogrammer/model.py
nqrduck_pulseprogrammer/pulseprogrammer.py
nqrduck_pulseprogrammer/view.py
nqrduck_pulseprogrammer/visual_parameter.py
nqrduck_pulseprogrammer/resources/pulseprogrammer.ini
nqrduck_pulseprogrammer-0.0.5.dist-info/METADATA
nqrduck_pulseprogrammer-0.0.5.dist-info/WHEEL
nqrduck_pulseprogrammer-0.0.5.dist-info/entry_points.txt
nqrduck_pulseprogrammer-0.0.5.dist-info/licenses/LICENSE
nqrduck_pulseprogrammer-0.0.5.dist-info/RECORD
