Metadata-Version: 2.4
Name: nqrduck-pulseprogrammer
Version: 0.0.5
Summary: A module for the NQRduck program (a simple python script™) to do pulse programming.
Project-URL: Homepage, https://nqrduck.cool
Project-URL: Bug Tracker, https://git.private.coffee/nqrduck/nqrduck-pulseprogrammer/issues
Project-URL: Source Code, https://git.private.coffee/nqrduck/nqrduck-pulseprogrammer
Author-email: jupfi <support@nqrduck.cool>
License: MIT License
License-File: LICENSE
Classifier: License :: OSI Approved :: MIT License
Classifier: Operating System :: OS Independent
Classifier: Programming Language :: Python :: 3
Requires-Python: >=3.10
Requires-Dist: matplotlib
Requires-Dist: nqrduck-spectrometer
Requires-Dist: pyqt6
Requires-Dist: quackseq
